ab_time_utils/__init__.py
ab_time_utils/timeUtil.py
ab_time_utils-0.2.1.dist-info/licenses/LICENSE.txt
src/__init__.py
src/timeUtil.py
ab_time_utils-0.2.1.dist-info/METADATA
ab_time_utils-0.2.1.dist-info/WHEEL
ab_time_utils-0.2.1.dist-info/top_level.txt
ab_time_utils-0.2.1.dist-info/RECORD
